[
  "occurrences":[{
                "occurrenceId": "Abarenicola claparedii 1",
                "eventId": null, 
                "institutionCode": null,
                "collectionCode": null,
                "catalogNumber": null, 
                "sex": null, 
                "lifeStage": null,
                "reproductiveCondition": null,
                "behavior": null, 
                "establishmentMeans": null, 
                "remarks": null,
                "countOfIndividuals": null,
                "preparations": null, 
                "fieldNotes": null,
                "samplingProtocol": null,
                "samplingEffort": null,
                "recordedBy": null,
                "identifiedBy": null,
                "dateIdentified": null,
                "eventDate": null,
                "modifiedDate": null, 
                "locality": "Asia",
                "decimalLatitude": "43.053837", 
                "decimalLongitude": null, 
                "verbatimLatitude": null, 
                "verbatimLongitude": null, 
                "verbatimElevation": null, 
                "deltaStatus": "insert"}],
 "associations": null,
  "measurementOrFacts": [{
                         "measurementId": "1", 
                         "occurrenceId": "Abarenicola claparedii 1",
                         "measurementOfTaxon": "true",
                         "associationId": null,
                         "parentMeasurementId": null,
                         "measurementType": "http://eol.org/schema/terms/MarineLarvalDevelopmentStrategy",
                         "measurementValue": "http://eol.org/schema/terms/lecithotrophic",
                         "unit": null,
                         "accuracy": null,
                         "statisticalMethod": null,
                         "determinedDate": null,
                         "determinedBy": null,
                         "measurementMethod": null,
                         "remarks": null,
                         "source": "http://datadryad.org/resource/doi:10.5061/dryad.m7j72",
                         "citation": "Dustin J. Marshall, Patrick J. Krug, Elena K. Kupriyanova, Maria Byrne, and Richard B. Emlet. 2012. The Biogeography of Marine Invertebrate Life Histories. Annual Review of Ecology, Evolution, and Systematics, Vol. 43: 97 -114. DOI: 10.1146/annurev-ecolsys-102710-145004",
                         "contributor": null,
                         "referenceId": "Okuda 1946",
                         "deltaStatus": null}]]

